pinterest/__init__.py
pinterest/config.py
pinterest/version.py
pinterest/ads/__init__.py
pinterest/ads/ad_accounts.py
pinterest/ads/ad_groups.py
pinterest/ads/ads.py
pinterest/ads/audiences.py
pinterest/ads/campaigns.py
pinterest/ads/conversion_events.py
pinterest/ads/conversion_tags.py
pinterest/ads/customer_lists.py
pinterest/ads/keywords.py
pinterest/bin/__init__.py
pinterest/bin/get_config.py
pinterest/client/__init__.py
pinterest/organic/__init__.py
pinterest/organic/boards.py
pinterest/organic/pins.py
pinterest/utils/__init__.py
pinterest/utils/base_model.py
pinterest/utils/bookmark.py
pinterest/utils/error_handling.py
pinterest/utils/load_json_config.py
pinterest/utils/refresh_access_token.py
pinterest/utils/sdk_exceptions.py
pinterest_api_sdk_symb_fork-0.2.3.dist-info/LICENSE
pinterest_api_sdk_symb_fork-0.2.3.dist-info/METADATA
pinterest_api_sdk_symb_fork-0.2.3.dist-info/WHEEL
pinterest_api_sdk_symb_fork-0.2.3.dist-info/top_level.txt
pinterest_api_sdk_symb_fork-0.2.3.dist-info/RECORD
