Metadata-Version: 2.1
Name: pinterest-api-sdk-symb-fork
Version: 0.2.3
Summary: Pinterest API SDK
Home-page: https://github.com/pinterest/pinterest-python-sdk
Author: Pinterest, Inc.
Author-email: sdk@pinterest.com
License: Apache License 2.0
License-File: LICENSE
Requires-Dist: urllib3==1.26.12
Requires-Dist: python-dateutil
Requires-Dist: python-dotenv>=0.20.0
Requires-Dist: six==1.16.0
Requires-Dist: Pinterest-Generated-Client==0.1.9
